{
  "required": true,
  "compatibilityLevel": "JAVA_11",
  "package": "io.github.betterclient.version.mixin",
  "minVersion": "0.8.5",
  "mixins": [
    "bridge.MixinCommandDispatcher",
    "bridge.MixinGameOptions",
    "bridge.MixinKeyBinding",
    "bridge.MixinMinecraftClient",
    "bridge.MixinMouse",
    "bridge.MixinWindow",
    "bridge.entity.MixinEntity",
    "bridge.entity.MixinPlayerEntity",
    "bridge.renderer.MixinBufferBuilder",
    "bridge.renderer.MixinDrawContext",
    "bridge.renderer.MixinMatrixStack",
    "bridge.renderer.MixinPostEffectProcessor",
    "bridge.renderer.MixinTextRenderer",
    "bridge.shader.MixinPostEffectPass",
    "client.MixinKeyBinding",
    "client.MixinMinecraftClient",
    "client.MixinMouse",
    "client.entity.MixinEndCrystal",
    "client.entity.MixinEntity",
    "client.entity.MixinItemEntity",
    "client.fixes.MixinLifecycledResourceManagerImpl",
    "client.fixes.MixinSoundManager",
    "client.fixes.MixinTranslationStorage",
    "client.gui.MixinInGameHud",
    "client.gui.MixinScreen",
    "client.gui.MixinSplashOverlay",
    "client.gui.MixinTitleScreen",
    "client.network.MixinClientConnection",
    "client.network.MixinCommandManager",
    "client.renderer.MixinCamera",
    "client.renderer.MixinEntityRenderer",
    "client.renderer.MixinGameRenderer",
    "client.renderer.MixinItemEntityRenderer"
  ]
}